README.md
setup.py
py_micro/__init__.py
py_micro/py_consul.py
py_micro/py_grpc.py
py_micro.egg-info/PKG-INFO
py_micro.egg-info/SOURCES.txt
py_micro.egg-info/dependency_links.txt
py_micro.egg-info/entry_points.txt
py_micro.egg-info/requires.txt
py_micro.egg-info/top_level.txt
py_micro.egg-info/zip-safe